{
  "levelId": 36,
  "foundationCount": 4,
  "columnCards": [
    4,
    5,
    6,
    7
  ],
  "maxMoves": 130,
  "data": [
    {
      "kind": 1,
      "wordVisualType": 0,
      "category": {
        "id": 3650,
        "elementCount": 5,
        "displayName": 65,
        "hasImage": 0
      }
    },
    {
      "kind": 1,
      "wordVisualType": 0,
      "category": {
        "id": 3637,
        "elementCount": 6,
        "displayName": 118,
        "hasImage": 0
      }
    },
    {
      "kind": 0,
      "wordVisualType": 0,
      "category": {
        "id": 3600,
        "elementCount": 7,
        "displayName": 162,
        "hasImage": 0
      },
      "wordText": "81X2"
    },
    {
      "kind": 0,
      "wordVisualType": 0,
      "category": {
        "id": 3623,
        "elementCount": 6,
        "displayName": 56,
        "hasImage": 0
      },
      "wordText": "52+4"
    },
    {
      "kind": 0,
      "wordVisualType": 0,
      "category": {
        "id": 3608,
        "elementCount": 7,
        "displayName": 45,
        "hasImage": 0
      },
      "wordText": "70-25"
    },
    {
      "kind": 1,
      "wordVisualType": 0,
      "category": {
        "id": 3600,
        "elementCount": 7,
        "displayName": 162,
        "hasImage": 0
      }
    },
    {
      "kind": 1,
      "wordVisualType": 0,
      "category": {
        "id": 3656,
        "elementCount": 4,
        "displayName": 88,
        "hasImage": 0
      }
    },
    {
      "kind": 0,
      "wordVisualType": 0,
      "category": {
        "id": 3630,
        "elementCount": 6,
        "displayName": 78,
        "hasImage": 0
      },
      "wordText": "88-10"
    },
    {
      "kind": 0,
      "wordVisualType": 0,
      "category": {
        "id": 3623,
        "elementCount": 6,
        "displayName": 56,
        "hasImage": 0
      },
      "wordText": "28+28"
    },
    {
      "kind": 0,
      "wordVisualType": 0,
      "category": {
        "id": 3623,
        "elementCount": 6,
        "displayName": 56,
        "hasImage": 0
      },
      "wordText": "64-8"
    },
    {
      "kind": 1,
      "wordVisualType": 0,
      "category": {
        "id": 3608,
        "elementCount": 7,
        "displayName": 45,
        "hasImage": 0
      }
    },
    {
      "kind": 0,
      "wordVisualType": 0,
      "category": {
        "id": 3637,
        "elementCount": 6,
        "displayName": 118,
        "hasImage": 0
      },
      "wordText": "236/2"
    },
    {
      "kind": 0,
      "wordVisualType": 0,
      "category": {
        "id": 3616,
        "elementCount": 6,
        "displayName": 24,
        "hasImage": 0
      },
      "wordText": "32-8"
    },
    {
      "kind": 0,
      "wordVisualType": 0,
      "category": {
        "id": 3670,
        "elementCount": 3,
        "displayName": 18,
        "hasImage": 0
      },
      "wordText": "9X2"
    },
    {
      "kind": 0,
      "wordVisualType": 0,
      "category": {
        "id": 3616,
        "elementCount": 6,
        "displayName": 24,
        "hasImage": 0
      },
      "wordText": "48/2"
    },
    {
      "kind": 0,
      "wordVisualType": 0,
      "category": {
        "id": 3644,
        "elementCount": 5,
        "displayName": 82,
        "hasImage": 0
      },
      "wordText": "41+41"
    },
    {
      "kind": 0,
      "wordVisualType": 0,
      "category": {
        "id": 3666,
        "elementCount": 3,
        "displayName": 12,
        "hasImage": 0
      },
      "wordText": "22-10"
    },
    {
      "kind": 0,
      "wordVisualType": 0,
      "category": {
        "id": 3608,
        "elementCount": 7,
        "displayName": 45,
        "hasImage": 0
      },
      "wordText": "60-15"
    },
    {
      "kind": 0,
      "wordVisualType": 0,
      "category": {
        "id": 3616,
        "elementCount": 6,
        "displayName": 24,
        "hasImage": 0
      },
      "wordText": "34-10"
    },
    {
      "kind": 1,
      "wordVisualType": 0,
      "category": {
        "id": 3644,
        "elementCount": 5,
        "displayName": 82,
        "hasImage": 0
      }
    },
    {
      "kind": 1,
      "wordVisualType": 0,
      "category": {
        "id": 3666,
        "elementCount": 3,
        "displayName": 12,
        "hasImage": 0
      }
    },
    {
      "kind": 0,
      "wordVisualType": 0,
      "category": {
        "id": 3630,
        "elementCount": 6,
        "displayName": 78,
        "hasImage": 0
      },
      "wordText": "74+4"
    },
    {
      "kind": 0,
      "wordVisualType": 0,
      "category": {
        "id": 3644,
        "elementCount": 5,
        "displayName": 82,
        "hasImage": 0
      },
      "wordText": "78+4"
    },
    {
      "kind": 1,
      "wordVisualType": 0,
      "category": {
        "id": 3670,
        "elementCount": 3,
        "displayName": 18,
        "hasImage": 0
      }
    },
    {
      "kind": 0,
      "wordVisualType": 0,
      "category": {
        "id": 3608,
        "elementCount": 7,
        "displayName": 45,
        "hasImage": 0
      },
      "wordText": "135/3"
    },
    {
      "kind": 0,
      "wordVisualType": 0,
      "category": {
        "id": 3644,
        "elementCount": 5,
        "displayName": 82,
        "hasImage": 0
      },
      "wordText": "164/2"
    },
    {
      "kind": 0,
      "wordVisualType": 0,
      "category": {
        "id": 3661,
        "elementCount": 4,
        "displayName": 96,
        "hasImage": 0
      },
      "wordText": "48X2"
    },
    {
      "kind": 0,
      "wordVisualType": 0,
      "category": {
        "id": 3600,
        "elementCount": 7,
        "displayName": 162,
        "hasImage": 0
      },
      "wordText": "171-9"
    },
    {
      "kind": 0,
      "wordVisualType": 0,
      "category": {
        "id": 3656,
        "elementCount": 4,
        "displayName": 88,
        "hasImage": 0
      },
      "wordText": "44+44"
    },
    {
      "kind": 0,
      "wordVisualType": 0,
      "category": {
        "id": 3637,
        "elementCount": 6,
        "displayName": 118,
        "hasImage": 0
      },
      "wordText": "114+4"
    },
    {
      "kind": 0,
      "wordVisualType": 0,
      "category": {
        "id": 3666,
        "elementCount": 3,
        "displayName": 12,
        "hasImage": 0
      },
      "wordText": "6+6"
    },
    {
      "kind": 0,
      "wordVisualType": 0,
      "category": {
        "id": 3637,
        "elementCount": 6,
        "displayName": 118,
        "hasImage": 0
      },
      "wordText": "126-8"
    },
    {
      "kind": 0,
      "wordVisualType": 0,
      "category": {
        "id": 3661,
        "elementCount": 4,
        "displayName": 96,
        "hasImage": 0
      },
      "wordText": "48+48"
    },
    {
      "kind": 1,
      "wordVisualType": 0,
      "category": {
        "id": 3630,
        "elementCount": 6,
        "displayName": 78,
        "hasImage": 0
      }
    },
    {
      "kind": 0,
      "wordVisualType": 0,
      "category": {
        "id": 3650,
        "elementCount": 5,
        "displayName": 65,
        "hasImage": 0
      },
      "wordText": "130/2"
    },
    {
      "kind": 0,
      "wordVisualType": 0,
      "category": {
        "id": 3650,
        "elementCount": 5,
        "displayName": 65,
        "hasImage": 0
      },
      "wordText": "13X5"
    },
    {
      "kind": 1,
      "wordVisualType": 0,
      "category": {
        "id": 3623,
        "elementCount": 6,
        "displayName": 56,
        "hasImage": 0
      }
    },
    {
      "kind": 0,
      "wordVisualType": 0,
      "category": {
        "id": 3600,
        "elementCount": 7,
        "displayName": 162,
        "hasImage": 0
      },
      "wordText": "158+4"
    },
    {
      "kind": 1,
      "wordVisualType": 0,
      "category": {
        "id": 3661,
        "elementCount": 4,
        "displayName": 96,
        "hasImage": 0
      }
    },
    {
      "kind": 0,
      "wordVisualType": 0,
      "category": {
        "id": 3650,
        "elementCount": 5,
        "displayName": 65,
        "hasImage": 0
      },
      "wordText": "50+15"
    },
    {
      "kind": 0,
      "wordVisualType": 0,
      "category": {
        "id": 3670,
        "elementCount": 3,
        "displayName": 18,
        "hasImage": 0
      },
      "wordText": "28-10"
    },
    {
      "kind": 0,
      "wordVisualType": 0,
      "category": {
        "id": 3608,
        "elementCount": 7,
        "displayName": 45,
        "hasImage": 0
      },
      "wordText": "9X5"
    },
    {
      "kind": 0,
      "wordVisualType": 0,
      "category": {
        "id": 3600,
        "elementCount": 7,
        "displayName": 162,
        "hasImage": 0
      },
      "wordText": "324/2"
    },
    {
      "kind": 0,
      "wordVisualType": 0,
      "category": {
        "id": 3600,
        "elementCount": 7,
        "displayName": 162,
        "hasImage": 0
      },
      "wordText": "486/3"
    },
    {
      "kind": 0,
      "wordVisualType": 0,
      "category": {
        "id": 3656,
        "elementCount": 4,
        "displayName": 88,
        "hasImage": 0
      },
      "wordText": "176/2"
    },
    {
      "kind": 0,
      "wordVisualType": 0,
      "category": {
        "id": 3600,
        "elementCount": 7,
        "displayName": 162,
        "hasImage": 0
      },
      "wordText": "170-8"
    },
    {
      "kind": 0,
      "wordVisualType": 0,
      "category": {
        "id": 3608,
        "elementCount": 7,
        "displayName": 45,
        "hasImage": 0
      },
      "wordText": "90/2"
    },
    {
      "kind": 0,
      "wordVisualType": 0,
      "category": {
        "id": 3650,
        "elementCount": 5,
        "displayName": 65,
        "hasImage": 0
      },
      "wordText": "90-25"
    },
    {
      "kind": 0,
      "wordVisualType": 0,
      "category": {
        "id": 3600,
        "elementCount": 7,
        "displayName": 162,
        "hasImage": 0
      },
      "wordText": "81+81"
    },
    {
      "kind": 0,
      "wordVisualType": 0,
      "category": {
        "id": 3637,
        "elementCount": 6,
        "displayName": 118,
        "hasImage": 0
      },
      "wordText": "127-9"
    },
    {
      "kind": 0,
      "wordVisualType": 0,
      "category": {
        "id": 3637,
        "elementCount": 6,
        "displayName": 118,
        "hasImage": 0
      },
      "wordText": "59X2"
    },
    {
      "kind": 0,
      "wordVisualType": 0,
      "category": {
        "id": 3616,
        "elementCount": 6,
        "displayName": 24,
        "hasImage": 0
      },
      "wordText": "20+4"
    },
    {
      "kind": 0,
      "wordVisualType": 0,
      "category": {
        "id": 3661,
        "elementCount": 4,
        "displayName": 96,
        "hasImage": 0
      },
      "wordText": "105-9"
    },
    {
      "kind": 0,
      "wordVisualType": 0,
      "category": {
        "id": 3630,
        "elementCount": 6,
        "displayName": 78,
        "hasImage": 0
      },
      "wordText": "39+39"
    },
    {
      "kind": 0,
      "wordVisualType": 0,
      "category": {
        "id": 3666,
        "elementCount": 3,
        "displayName": 12,
        "hasImage": 0
      },
      "wordText": "6X2"
    },
    {
      "kind": 0,
      "wordVisualType": 0,
      "category": {
        "id": 3616,
        "elementCount": 6,
        "displayName": 24,
        "hasImage": 0
      },
      "wordText": "12X2"
    },
    {
      "kind": 0,
      "wordVisualType": 0,
      "category": {
        "id": 3656,
        "elementCount": 4,
        "displayName": 88,
        "hasImage": 0
      },
      "wordText": "44X2"
    },
    {
      "kind": 0,
      "wordVisualType": 0,
      "category": {
        "id": 3623,
        "elementCount": 6,
        "displayName": 56,
        "hasImage": 0
      },
      "wordText": "112/2"
    },
    {
      "kind": 0,
      "wordVisualType": 0,
      "category": {
        "id": 3644,
        "elementCount": 5,
        "displayName": 82,
        "hasImage": 0
      },
      "wordText": "41X2"
    },
    {
      "kind": 1,
      "wordVisualType": 0,
      "category": {
        "id": 3616,
        "elementCount": 6,
        "displayName": 24,
        "hasImage": 0
      }
    },
    {
      "kind": 0,
      "wordVisualType": 0,
      "category": {
        "id": 3661,
        "elementCount": 4,
        "displayName": 96,
        "hasImage": 0
      },
      "wordText": "192/2"
    },
    {
      "kind": 0,
      "wordVisualType": 0,
      "category": {
        "id": 3637,
        "elementCount": 6,
        "displayName": 118,
        "hasImage": 0
      },
      "wordText": "59+59"
    },
    {
      "kind": 0,
      "wordVisualType": 0,
      "category": {
        "id": 3623,
        "elementCount": 6,
        "displayName": 56,
        "hasImage": 0
      },
      "wordText": "28X2"
    },
    {
      "kind": 0,
      "wordVisualType": 0,
      "category": {
        "id": 3650,
        "elementCount": 5,
        "displayName": 65,
        "hasImage": 0
      },
      "wordText": "60+5"
    },
    {
      "kind": 0,
      "wordVisualType": 0,
      "category": {
        "id": 3670,
        "elementCount": 3,
        "displayName": 18,
        "hasImage": 0
      },
      "wordText": "9+9"
    },
    {
      "kind": 0,
      "wordVisualType": 0,
      "category": {
        "id": 3630,
        "elementCount": 6,
        "displayName": 78,
        "hasImage": 0
      },
      "wordText": "156/2"
    },
    {
      "kind": 0,
      "wordVisualType": 0,
      "category": {
        "id": 3608,
        "elementCount": 7,
        "displayName": 45,
        "hasImage": 0
      },
      "wordText": "30+15"
    },
    {
      "kind": 0,
      "wordVisualType": 0,
      "category": {
        "id": 3656,
        "elementCount": 4,
        "displayName": 88,
        "hasImage": 0
      },
      "wordText": "98-10"
    },
    {
      "kind": 0,
      "wordVisualType": 0,
      "category": {
        "id": 3630,
        "elementCount": 6,
        "displayName": 78,
        "hasImage": 0
      },
      "wordText": "39X2"
    },
    {
      "kind": 0,
      "wordVisualType": 0,
      "category": {
        "id": 3644,
        "elementCount": 5,
        "displayName": 82,
        "hasImage": 0
      },
      "wordText": "92-10"
    },
    {
      "kind": 0,
      "wordVisualType": 0,
      "category": {
        "id": 3608,
        "elementCount": 7,
        "displayName": 45,
        "hasImage": 0
      },
      "wordText": "40+5"
    },
    {
      "kind": 0,
      "wordVisualType": 0,
      "category": {
        "id": 3630,
        "elementCount": 6,
        "displayName": 78,
        "hasImage": 0
      },
      "wordText": "86-8"
    },
    {
      "kind": 0,
      "wordVisualType": 0,
      "category": {
        "id": 3616,
        "elementCount": 6,
        "displayName": 24,
        "hasImage": 0
      },
      "wordText": "12+12"
    },
    {
      "kind": 0,
      "wordVisualType": 0,
      "category": {
        "id": 3623,
        "elementCount": 6,
        "displayName": 56,
        "hasImage": 0
      },
      "wordText": "66-10"
    }
  ]
}