{
  "levelId": 219,
  "foundationCount": 5,
  "columnCards": [
    5,
    6,
    7,
    8,
    9
  ],
  "maxMoves": 135,
  "data": [
    {
      "kind": 1,
      "wordVisualType": 0,
      "category": {
        "id": 21952,
        "elementCount": 5,
        "displayName": 36,
        "hasImage": 0
      }
    },
    {
      "kind": 0,
      "wordVisualType": 0,
      "category": {
        "id": 21918,
        "elementCount": 7,
        "displayName": 132,
        "hasImage": 0
      },
      "wordText": "660/5"
    },
    {
      "kind": 1,
      "wordVisualType": 0,
      "category": {
        "id": 21946,
        "elementCount": 5,
        "displayName": 56,
        "hasImage": 0
      }
    },
    {
      "kind": 0,
      "wordVisualType": 0,
      "category": {
        "id": 21909,
        "elementCount": 8,
        "displayName": 154,
        "hasImage": 0
      },
      "wordText": "616/4"
    },
    {
      "kind": 0,
      "wordVisualType": 0,
      "category": {
        "id": 21934,
        "elementCount": 5,
        "displayName": 92,
        "hasImage": 0
      },
      "wordText": "11+81"
    },
    {
      "kind": 0,
      "wordVisualType": 0,
      "category": {
        "id": 21926,
        "elementCount": 7,
        "displayName": 108,
        "hasImage": 0
      },
      "wordText": "6+102"
    },
    {
      "kind": 0,
      "wordVisualType": 0,
      "category": {
        "id": 21958,
        "elementCount": 4,
        "displayName": 24,
        "hasImage": 0
      },
      "wordText": "3X8"
    },
    {
      "kind": 0,
      "wordVisualType": 0,
      "category": {
        "id": 21900,
        "elementCount": 8,
        "displayName": 186,
        "hasImage": 0
      },
      "wordText": "3X62"
    },
    {
      "kind": 0,
      "wordVisualType": 0,
      "category": {
        "id": 21934,
        "elementCount": 5,
        "displayName": 92,
        "hasImage": 0
      },
      "wordText": "460/5"
    },
    {
      "kind": 0,
      "wordVisualType": 0,
      "category": {
        "id": 21909,
        "elementCount": 8,
        "displayName": 154,
        "hasImage": 0
      },
      "wordText": "158-4"
    },
    {
      "kind": 0,
      "wordVisualType": 0,
      "category": {
        "id": 21909,
        "elementCount": 8,
        "displayName": 154,
        "hasImage": 0
      },
      "wordText": "145+9"
    },
    {
      "kind": 0,
      "wordVisualType": 0,
      "category": {
        "id": 21946,
        "elementCount": 5,
        "displayName": 56,
        "hasImage": 0
      },
      "wordText": "112/2"
    },
    {
      "kind": 0,
      "wordVisualType": 0,
      "category": {
        "id": 21918,
        "elementCount": 7,
        "displayName": 132,
        "hasImage": 0
      },
      "wordText": "33+99"
    },
    {
      "kind": 0,
      "wordVisualType": 0,
      "category": {
        "id": 21958,
        "elementCount": 4,
        "displayName": 24,
        "hasImage": 0
      },
      "wordText": "34-10"
    },
    {
      "kind": 0,
      "wordVisualType": 0,
      "category": {
        "id": 21900,
        "elementCount": 8,
        "displayName": 186,
        "hasImage": 0
      },
      "wordText": "558/3"
    },
    {
      "kind": 0,
      "wordVisualType": 0,
      "category": {
        "id": 21952,
        "elementCount": 5,
        "displayName": 36,
        "hasImage": 0
      },
      "wordText": "180/5"
    },
    {
      "kind": 0,
      "wordVisualType": 0,
      "category": {
        "id": 21900,
        "elementCount": 8,
        "displayName": 186,
        "hasImage": 0
      },
      "wordText": "194-8"
    },
    {
      "kind": 0,
      "wordVisualType": 0,
      "category": {
        "id": 21918,
        "elementCount": 7,
        "displayName": 132,
        "hasImage": 0
      },
      "wordText": "2X66"
    },
    {
      "kind": 0,
      "wordVisualType": 0,
      "category": {
        "id": 21934,
        "elementCount": 5,
        "displayName": 92,
        "hasImage": 0
      },
      "wordText": "184/2"
    },
    {
      "kind": 0,
      "wordVisualType": 0,
      "category": {
        "id": 21963,
        "elementCount": 4,
        "displayName": 18,
        "hasImage": 0
      },
      "wordText": "126/7"
    },
    {
      "kind": 0,
      "wordVisualType": 0,
      "category": {
        "id": 21926,
        "elementCount": 7,
        "displayName": 108,
        "hasImage": 0
      },
      "wordText": "756/7"
    },
    {
      "kind": 0,
      "wordVisualType": 0,
      "category": {
        "id": 21963,
        "elementCount": 4,
        "displayName": 18,
        "hasImage": 0
      },
      "wordText": "7+11"
    },
    {
      "kind": 0,
      "wordVisualType": 0,
      "category": {
        "id": 21900,
        "elementCount": 8,
        "displayName": 186,
        "hasImage": 0
      },
      "wordText": "89+97"
    },
    {
      "kind": 0,
      "wordVisualType": 0,
      "category": {
        "id": 21952,
        "elementCount": 5,
        "displayName": 36,
        "hasImage": 0
      },
      "wordText": "47-11"
    },
    {
      "kind": 1,
      "wordVisualType": 0,
      "category": {
        "id": 21963,
        "elementCount": 4,
        "displayName": 18,
        "hasImage": 0
      }
    },
    {
      "kind": 1,
      "wordVisualType": 0,
      "category": {
        "id": 21909,
        "elementCount": 8,
        "displayName": 154,
        "hasImage": 0
      }
    },
    {
      "kind": 1,
      "wordVisualType": 0,
      "category": {
        "id": 21918,
        "elementCount": 7,
        "displayName": 132,
        "hasImage": 0
      }
    },
    {
      "kind": 0,
      "wordVisualType": 0,
      "category": {
        "id": 21909,
        "elementCount": 8,
        "displayName": 154,
        "hasImage": 0
      },
      "wordText": "7X22"
    },
    {
      "kind": 0,
      "wordVisualType": 0,
      "category": {
        "id": 21918,
        "elementCount": 7,
        "displayName": 132,
        "hasImage": 0
      },
      "wordText": "3X44"
    },
    {
      "kind": 0,
      "wordVisualType": 0,
      "category": {
        "id": 21963,
        "elementCount": 4,
        "displayName": 18,
        "hasImage": 0
      },
      "wordText": "35-17"
    },
    {
      "kind": 1,
      "wordVisualType": 0,
      "category": {
        "id": 21958,
        "elementCount": 4,
        "displayName": 24,
        "hasImage": 0
      }
    },
    {
      "kind": 0,
      "wordVisualType": 0,
      "category": {
        "id": 21918,
        "elementCount": 7,
        "displayName": 132,
        "hasImage": 0
      },
      "wordText": "528/4"
    },
    {
      "kind": 0,
      "wordVisualType": 0,
      "category": {
        "id": 21963,
        "elementCount": 4,
        "displayName": 18,
        "hasImage": 0
      },
      "wordText": "3X6"
    },
    {
      "kind": 0,
      "wordVisualType": 0,
      "category": {
        "id": 21952,
        "elementCount": 5,
        "displayName": 36,
        "hasImage": 0
      },
      "wordText": "12+24"
    },
    {
      "kind": 0,
      "wordVisualType": 0,
      "category": {
        "id": 21909,
        "elementCount": 8,
        "displayName": 154,
        "hasImage": 0
      },
      "wordText": "924/6"
    },
    {
      "kind": 0,
      "wordVisualType": 0,
      "category": {
        "id": 21940,
        "elementCount": 5,
        "displayName": 72,
        "hasImage": 0
      },
      "wordText": "10+62"
    },
    {
      "kind": 0,
      "wordVisualType": 0,
      "category": {
        "id": 21926,
        "elementCount": 7,
        "displayName": 108,
        "hasImage": 0
      },
      "wordText": "117-9"
    },
    {
      "kind": 0,
      "wordVisualType": 0,
      "category": {
        "id": 21900,
        "elementCount": 8,
        "displayName": 186,
        "hasImage": 0
      },
      "wordText": "190-4"
    },
    {
      "kind": 0,
      "wordVisualType": 0,
      "category": {
        "id": 21940,
        "elementCount": 5,
        "displayName": 72,
        "hasImage": 0
      },
      "wordText": "86-14"
    },
    {
      "kind": 0,
      "wordVisualType": 0,
      "category": {
        "id": 21900,
        "elementCount": 8,
        "displayName": 186,
        "hasImage": 0
      },
      "wordText": "930/5"
    },
    {
      "kind": 0,
      "wordVisualType": 0,
      "category": {
        "id": 21926,
        "elementCount": 7,
        "displayName": 108,
        "hasImage": 0
      },
      "wordText": "102+6"
    },
    {
      "kind": 0,
      "wordVisualType": 0,
      "category": {
        "id": 21958,
        "elementCount": 4,
        "displayName": 24,
        "hasImage": 0
      },
      "wordText": "144/6"
    },
    {
      "kind": 1,
      "wordVisualType": 0,
      "category": {
        "id": 21940,
        "elementCount": 5,
        "displayName": 72,
        "hasImage": 0
      }
    },
    {
      "kind": 0,
      "wordVisualType": 0,
      "category": {
        "id": 21900,
        "elementCount": 8,
        "displayName": 186,
        "hasImage": 0
      },
      "wordText": "88+98"
    },
    {
      "kind": 0,
      "wordVisualType": 0,
      "category": {
        "id": 21909,
        "elementCount": 8,
        "displayName": 154,
        "hasImage": 0
      },
      "wordText": "157-3"
    },
    {
      "kind": 1,
      "wordVisualType": 0,
      "category": {
        "id": 21934,
        "elementCount": 5,
        "displayName": 92,
        "hasImage": 0
      }
    },
    {
      "kind": 0,
      "wordVisualType": 0,
      "category": {
        "id": 21952,
        "elementCount": 5,
        "displayName": 36,
        "hasImage": 0
      },
      "wordText": "4X9"
    },
    {
      "kind": 0,
      "wordVisualType": 0,
      "category": {
        "id": 21952,
        "elementCount": 5,
        "displayName": 36,
        "hasImage": 0
      },
      "wordText": "144/4"
    },
    {
      "kind": 0,
      "wordVisualType": 0,
      "category": {
        "id": 21900,
        "elementCount": 8,
        "displayName": 186,
        "hasImage": 0
      },
      "wordText": "2X93"
    },
    {
      "kind": 0,
      "wordVisualType": 0,
      "category": {
        "id": 21940,
        "elementCount": 5,
        "displayName": 72,
        "hasImage": 0
      },
      "wordText": "14+58"
    },
    {
      "kind": 1,
      "wordVisualType": 0,
      "category": {
        "id": 21900,
        "elementCount": 8,
        "displayName": 186,
        "hasImage": 0
      }
    },
    {
      "kind": 0,
      "wordVisualType": 0,
      "category": {
        "id": 21940,
        "elementCount": 5,
        "displayName": 72,
        "hasImage": 0
      },
      "wordText": "288/4"
    },
    {
      "kind": 0,
      "wordVisualType": 0,
      "category": {
        "id": 21926,
        "elementCount": 7,
        "displayName": 108,
        "hasImage": 0
      },
      "wordText": "2X54"
    },
    {
      "kind": 1,
      "wordVisualType": 0,
      "category": {
        "id": 21926,
        "elementCount": 7,
        "displayName": 108,
        "hasImage": 0
      }
    },
    {
      "kind": 0,
      "wordVisualType": 0,
      "category": {
        "id": 21909,
        "elementCount": 8,
        "displayName": 154,
        "hasImage": 0
      },
      "wordText": "62+92"
    },
    {
      "kind": 0,
      "wordVisualType": 0,
      "category": {
        "id": 21958,
        "elementCount": 4,
        "displayName": 24,
        "hasImage": 0
      },
      "wordText": "11+13"
    },
    {
      "kind": 0,
      "wordVisualType": 0,
      "category": {
        "id": 21946,
        "elementCount": 5,
        "displayName": 56,
        "hasImage": 0
      },
      "wordText": "66-10"
    },
    {
      "kind": 0,
      "wordVisualType": 0,
      "category": {
        "id": 21909,
        "elementCount": 8,
        "displayName": 154,
        "hasImage": 0
      },
      "wordText": "2X77"
    },
    {
      "kind": 0,
      "wordVisualType": 0,
      "category": {
        "id": 21934,
        "elementCount": 5,
        "displayName": 92,
        "hasImage": 0
      },
      "wordText": "101-9"
    },
    {
      "kind": 0,
      "wordVisualType": 0,
      "category": {
        "id": 21918,
        "elementCount": 7,
        "displayName": 132,
        "hasImage": 0
      },
      "wordText": "139-7"
    },
    {
      "kind": 0,
      "wordVisualType": 0,
      "category": {
        "id": 21926,
        "elementCount": 7,
        "displayName": 108,
        "hasImage": 0
      },
      "wordText": "4X27"
    },
    {
      "kind": 0,
      "wordVisualType": 0,
      "category": {
        "id": 21946,
        "elementCount": 5,
        "displayName": 56,
        "hasImage": 0
      },
      "wordText": "12+44"
    },
    {
      "kind": 0,
      "wordVisualType": 0,
      "category": {
        "id": 21934,
        "elementCount": 5,
        "displayName": 92,
        "hasImage": 0
      },
      "wordText": "2X46"
    },
    {
      "kind": 0,
      "wordVisualType": 0,
      "category": {
        "id": 21926,
        "elementCount": 7,
        "displayName": 108,
        "hasImage": 0
      },
      "wordText": "540/5"
    },
    {
      "kind": 0,
      "wordVisualType": 0,
      "category": {
        "id": 21918,
        "elementCount": 7,
        "displayName": 132,
        "hasImage": 0
      },
      "wordText": "34+98"
    },
    {
      "kind": 0,
      "wordVisualType": 0,
      "category": {
        "id": 21940,
        "elementCount": 5,
        "displayName": 72,
        "hasImage": 0
      },
      "wordText": "8X9"
    },
    {
      "kind": 0,
      "wordVisualType": 0,
      "category": {
        "id": 21946,
        "elementCount": 5,
        "displayName": 56,
        "hasImage": 0
      },
      "wordText": "2X28"
    },
    {
      "kind": 0,
      "wordVisualType": 0,
      "category": {
        "id": 21946,
        "elementCount": 5,
        "displayName": 56,
        "hasImage": 0
      },
      "wordText": "67-11"
    }
  ]
}