{
  "levelId": 468,
  "foundationCount": 5,
  "columnCards": [
    5,
    6,
    7,
    8,
    9
  ],
  "maxMoves": 128,
  "data": [
    {
      "kind": 0,
      "wordVisualType": 0,
      "category": {
        "id": 46809,
        "elementCount": 8,
        "displayName": 154,
        "hasImage": 0
      },
      "wordText": "462/3"
    },
    {
      "kind": 0,
      "wordVisualType": 0,
      "category": {
        "id": 46841,
        "elementCount": 4,
        "displayName": 36,
        "hasImage": 0
      },
      "wordText": "15+21"
    },
    {
      "kind": 0,
      "wordVisualType": 0,
      "category": {
        "id": 46800,
        "elementCount": 8,
        "displayName": 198,
        "hasImage": 0
      },
      "wordText": "190+8"
    },
    {
      "kind": 0,
      "wordVisualType": 0,
      "category": {
        "id": 46809,
        "elementCount": 8,
        "displayName": 154,
        "hasImage": 0
      },
      "wordText": "59+95"
    },
    {
      "kind": 0,
      "wordVisualType": 0,
      "category": {
        "id": 46809,
        "elementCount": 8,
        "displayName": 154,
        "hasImage": 0
      },
      "wordText": "60+94"
    },
    {
      "kind": 1,
      "wordVisualType": 0,
      "category": {
        "id": 46841,
        "elementCount": 4,
        "displayName": 36,
        "hasImage": 0
      }
    },
    {
      "kind": 0,
      "wordVisualType": 0,
      "category": {
        "id": 46800,
        "elementCount": 8,
        "displayName": 198,
        "hasImage": 0
      },
      "wordText": "202-4"
    },
    {
      "kind": 0,
      "wordVisualType": 0,
      "category": {
        "id": 46800,
        "elementCount": 8,
        "displayName": 198,
        "hasImage": 0
      },
      "wordText": "203-5"
    },
    {
      "kind": 1,
      "wordVisualType": 0,
      "category": {
        "id": 46834,
        "elementCount": 6,
        "displayName": 66,
        "hasImage": 0
      }
    },
    {
      "kind": 1,
      "wordVisualType": 0,
      "category": {
        "id": 46800,
        "elementCount": 8,
        "displayName": 198,
        "hasImage": 0
      }
    },
    {
      "kind": 1,
      "wordVisualType": 0,
      "category": {
        "id": 46818,
        "elementCount": 8,
        "displayName": 114,
        "hasImage": 0
      }
    },
    {
      "kind": 1,
      "wordVisualType": 0,
      "category": {
        "id": 46827,
        "elementCount": 6,
        "displayName": 92,
        "hasImage": 0
      }
    },
    {
      "kind": 0,
      "wordVisualType": 0,
      "category": {
        "id": 46809,
        "elementCount": 8,
        "displayName": 154,
        "hasImage": 0
      },
      "wordText": "308/2"
    },
    {
      "kind": 0,
      "wordVisualType": 0,
      "category": {
        "id": 46841,
        "elementCount": 4,
        "displayName": 36,
        "hasImage": 0
      },
      "wordText": "144/4"
    },
    {
      "kind": 0,
      "wordVisualType": 0,
      "category": {
        "id": 46841,
        "elementCount": 4,
        "displayName": 36,
        "hasImage": 0
      },
      "wordText": "4X9"
    },
    {
      "kind": 0,
      "wordVisualType": 0,
      "category": {
        "id": 46800,
        "elementCount": 8,
        "displayName": 198,
        "hasImage": 0
      },
      "wordText": "792/4"
    },
    {
      "kind": 0,
      "wordVisualType": 0,
      "category": {
        "id": 46809,
        "elementCount": 8,
        "displayName": 154,
        "hasImage": 0
      },
      "wordText": "7X22"
    },
    {
      "kind": 1,
      "wordVisualType": 0,
      "category": {
        "id": 46809,
        "elementCount": 8,
        "displayName": 154,
        "hasImage": 0
      }
    },
    {
      "kind": 0,
      "wordVisualType": 0,
      "category": {
        "id": 46800,
        "elementCount": 8,
        "displayName": 198,
        "hasImage": 0
      },
      "wordText": "99+99"
    },
    {
      "kind": 0,
      "wordVisualType": 0,
      "category": {
        "id": 46800,
        "elementCount": 8,
        "displayName": 198,
        "hasImage": 0
      },
      "wordText": "3X66"
    },
    {
      "kind": 0,
      "wordVisualType": 0,
      "category": {
        "id": 46809,
        "elementCount": 8,
        "displayName": 154,
        "hasImage": 0
      },
      "wordText": "158-4"
    },
    {
      "kind": 0,
      "wordVisualType": 0,
      "category": {
        "id": 46800,
        "elementCount": 8,
        "displayName": 198,
        "hasImage": 0
      },
      "wordText": "396/2"
    },
    {
      "kind": 0,
      "wordVisualType": 0,
      "category": {
        "id": 46809,
        "elementCount": 8,
        "displayName": 154,
        "hasImage": 0
      },
      "wordText": "157-3"
    },
    {
      "kind": 0,
      "wordVisualType": 0,
      "category": {
        "id": 46841,
        "elementCount": 4,
        "displayName": 36,
        "hasImage": 0
      },
      "wordText": "49-13"
    },
    {
      "kind": 0,
      "wordVisualType": 0,
      "category": {
        "id": 46800,
        "elementCount": 8,
        "displayName": 198,
        "hasImage": 0
      },
      "wordText": "2X99"
    },
    {
      "kind": 0,
      "wordVisualType": 0,
      "category": {
        "id": 46809,
        "elementCount": 8,
        "displayName": 154,
        "hasImage": 0
      },
      "wordText": "2X77"
    },
    {
      "kind": 0,
      "wordVisualType": 0,
      "category": {
        "id": 46818,
        "elementCount": 8,
        "displayName": 114,
        "hasImage": 0
      },
      "wordText": "23+91"
    },
    {
      "kind": 0,
      "wordVisualType": 0,
      "category": {
        "id": 46846,
        "elementCount": 4,
        "displayName": 18,
        "hasImage": 0
      },
      "wordText": "2X9"
    },
    {
      "kind": 0,
      "wordVisualType": 0,
      "category": {
        "id": 46827,
        "elementCount": 6,
        "displayName": 92,
        "hasImage": 0
      },
      "wordText": "4X23"
    },
    {
      "kind": 0,
      "wordVisualType": 0,
      "category": {
        "id": 46846,
        "elementCount": 4,
        "displayName": 18,
        "hasImage": 0
      },
      "wordText": "162/9"
    },
    {
      "kind": 0,
      "wordVisualType": 0,
      "category": {
        "id": 46827,
        "elementCount": 6,
        "displayName": 92,
        "hasImage": 0
      },
      "wordText": "368/4"
    },
    {
      "kind": 0,
      "wordVisualType": 0,
      "category": {
        "id": 46827,
        "elementCount": 6,
        "displayName": 92,
        "hasImage": 0
      },
      "wordText": "14+78"
    },
    {
      "kind": 0,
      "wordVisualType": 0,
      "category": {
        "id": 46834,
        "elementCount": 6,
        "displayName": 66,
        "hasImage": 0
      },
      "wordText": "14+52"
    },
    {
      "kind": 0,
      "wordVisualType": 0,
      "category": {
        "id": 46834,
        "elementCount": 6,
        "displayName": 66,
        "hasImage": 0
      },
      "wordText": "82-16"
    },
    {
      "kind": 0,
      "wordVisualType": 0,
      "category": {
        "id": 46818,
        "elementCount": 8,
        "displayName": 114,
        "hasImage": 0
      },
      "wordText": "2X57"
    },
    {
      "kind": 0,
      "wordVisualType": 0,
      "category": {
        "id": 46834,
        "elementCount": 6,
        "displayName": 66,
        "hasImage": 0
      },
      "wordText": "11+55"
    },
    {
      "kind": 1,
      "wordVisualType": 0,
      "category": {
        "id": 46846,
        "elementCount": 4,
        "displayName": 18,
        "hasImage": 0
      }
    },
    {
      "kind": 0,
      "wordVisualType": 0,
      "category": {
        "id": 46818,
        "elementCount": 8,
        "displayName": 114,
        "hasImage": 0
      },
      "wordText": "122-8"
    },
    {
      "kind": 0,
      "wordVisualType": 0,
      "category": {
        "id": 46818,
        "elementCount": 8,
        "displayName": 114,
        "hasImage": 0
      },
      "wordText": "684/6"
    },
    {
      "kind": 0,
      "wordVisualType": 0,
      "category": {
        "id": 46818,
        "elementCount": 8,
        "displayName": 114,
        "hasImage": 0
      },
      "wordText": "120-6"
    },
    {
      "kind": 0,
      "wordVisualType": 0,
      "category": {
        "id": 46827,
        "elementCount": 6,
        "displayName": 92,
        "hasImage": 0
      },
      "wordText": "96-4"
    },
    {
      "kind": 0,
      "wordVisualType": 0,
      "category": {
        "id": 46818,
        "elementCount": 8,
        "displayName": 114,
        "hasImage": 0
      },
      "wordText": "456/4"
    },
    {
      "kind": 0,
      "wordVisualType": 0,
      "category": {
        "id": 46834,
        "elementCount": 6,
        "displayName": 66,
        "hasImage": 0
      },
      "wordText": "3X22"
    },
    {
      "kind": 0,
      "wordVisualType": 0,
      "category": {
        "id": 46827,
        "elementCount": 6,
        "displayName": 92,
        "hasImage": 0
      },
      "wordText": "552/6"
    },
    {
      "kind": 0,
      "wordVisualType": 0,
      "category": {
        "id": 46846,
        "elementCount": 4,
        "displayName": 18,
        "hasImage": 0
      },
      "wordText": "39-21"
    },
    {
      "kind": 0,
      "wordVisualType": 0,
      "category": {
        "id": 46818,
        "elementCount": 8,
        "displayName": 114,
        "hasImage": 0
      },
      "wordText": "3X38"
    },
    {
      "kind": 0,
      "wordVisualType": 0,
      "category": {
        "id": 46834,
        "elementCount": 6,
        "displayName": 66,
        "hasImage": 0
      },
      "wordText": "264/4"
    },
    {
      "kind": 0,
      "wordVisualType": 0,
      "category": {
        "id": 46818,
        "elementCount": 8,
        "displayName": 114,
        "hasImage": 0
      },
      "wordText": "22+92"
    },
    {
      "kind": 0,
      "wordVisualType": 0,
      "category": {
        "id": 46827,
        "elementCount": 6,
        "displayName": 92,
        "hasImage": 0
      },
      "wordText": "12+80"
    },
    {
      "kind": 0,
      "wordVisualType": 0,
      "category": {
        "id": 46834,
        "elementCount": 6,
        "displayName": 66,
        "hasImage": 0
      },
      "wordText": "79-13"
    },
    {
      "kind": 0,
      "wordVisualType": 0,
      "category": {
        "id": 46846,
        "elementCount": 4,
        "displayName": 18,
        "hasImage": 0
      },
      "wordText": "15+3"
    }
  ]
}