{
  "levelId": 446,
  "foundationCount": 5,
  "columnCards": [
    5,
    6,
    7,
    8,
    9
  ],
  "maxMoves": 115,
  "data": [
    {
      "kind": 0,
      "wordVisualType": 0,
      "category": {
        "id": 44609,
        "elementCount": 8,
        "displayName": 132,
        "hasImage": 0
      },
      "wordText": "136-4"
    },
    {
      "kind": 0,
      "wordVisualType": 0,
      "category": {
        "id": 44627,
        "elementCount": 6,
        "displayName": 64,
        "hasImage": 0
      },
      "wordText": "2X32"
    },
    {
      "kind": 0,
      "wordVisualType": 0,
      "category": {
        "id": 44609,
        "elementCount": 8,
        "displayName": 132,
        "hasImage": 0
      },
      "wordText": "140-8"
    },
    {
      "kind": 0,
      "wordVisualType": 0,
      "category": {
        "id": 44609,
        "elementCount": 8,
        "displayName": 132,
        "hasImage": 0
      },
      "wordText": "36+96"
    },
    {
      "kind": 1,
      "wordVisualType": 0,
      "category": {
        "id": 44641,
        "elementCount": 4,
        "displayName": 18,
        "hasImage": 0
      }
    },
    {
      "kind": 0,
      "wordVisualType": 0,
      "category": {
        "id": 44641,
        "elementCount": 4,
        "displayName": 18,
        "hasImage": 0
      },
      "wordText": "14+4"
    },
    {
      "kind": 1,
      "wordVisualType": 0,
      "category": {
        "id": 44634,
        "elementCount": 6,
        "displayName": 32,
        "hasImage": 0
      }
    },
    {
      "kind": 0,
      "wordVisualType": 0,
      "category": {
        "id": 44627,
        "elementCount": 6,
        "displayName": 64,
        "hasImage": 0
      },
      "wordText": "77-13"
    },
    {
      "kind": 0,
      "wordVisualType": 0,
      "category": {
        "id": 44609,
        "elementCount": 8,
        "displayName": 132,
        "hasImage": 0
      },
      "wordText": "4X33"
    },
    {
      "kind": 0,
      "wordVisualType": 0,
      "category": {
        "id": 44627,
        "elementCount": 6,
        "displayName": 64,
        "hasImage": 0
      },
      "wordText": "74-10"
    },
    {
      "kind": 0,
      "wordVisualType": 0,
      "category": {
        "id": 44641,
        "elementCount": 4,
        "displayName": 18,
        "hasImage": 0
      },
      "wordText": "35-17"
    },
    {
      "kind": 0,
      "wordVisualType": 0,
      "category": {
        "id": 44600,
        "elementCount": 8,
        "displayName": 176,
        "hasImage": 0
      },
      "wordText": "880/5"
    },
    {
      "kind": 0,
      "wordVisualType": 0,
      "category": {
        "id": 44609,
        "elementCount": 8,
        "displayName": 132,
        "hasImage": 0
      },
      "wordText": "660/5"
    },
    {
      "kind": 0,
      "wordVisualType": 0,
      "category": {
        "id": 44641,
        "elementCount": 4,
        "displayName": 18,
        "hasImage": 0
      },
      "wordText": "2X9"
    },
    {
      "kind": 0,
      "wordVisualType": 0,
      "category": {
        "id": 44627,
        "elementCount": 6,
        "displayName": 64,
        "hasImage": 0
      },
      "wordText": "192/3"
    },
    {
      "kind": 0,
      "wordVisualType": 0,
      "category": {
        "id": 44641,
        "elementCount": 4,
        "displayName": 18,
        "hasImage": 0
      },
      "wordText": "126/7"
    },
    {
      "kind": 0,
      "wordVisualType": 0,
      "category": {
        "id": 44609,
        "elementCount": 8,
        "displayName": 132,
        "hasImage": 0
      },
      "wordText": "528/4"
    },
    {
      "kind": 1,
      "wordVisualType": 0,
      "category": {
        "id": 44618,
        "elementCount": 8,
        "displayName": 96,
        "hasImage": 0
      }
    },
    {
      "kind": 1,
      "wordVisualType": 0,
      "category": {
        "id": 44609,
        "elementCount": 8,
        "displayName": 132,
        "hasImage": 0
      }
    },
    {
      "kind": 1,
      "wordVisualType": 0,
      "category": {
        "id": 44600,
        "elementCount": 8,
        "displayName": 176,
        "hasImage": 0
      }
    },
    {
      "kind": 0,
      "wordVisualType": 0,
      "category": {
        "id": 44627,
        "elementCount": 6,
        "displayName": 64,
        "hasImage": 0
      },
      "wordText": "12+52"
    },
    {
      "kind": 0,
      "wordVisualType": 0,
      "category": {
        "id": 44609,
        "elementCount": 8,
        "displayName": 132,
        "hasImage": 0
      },
      "wordText": "123+9"
    },
    {
      "kind": 0,
      "wordVisualType": 0,
      "category": {
        "id": 44627,
        "elementCount": 6,
        "displayName": 64,
        "hasImage": 0
      },
      "wordText": "8X8"
    },
    {
      "kind": 1,
      "wordVisualType": 0,
      "category": {
        "id": 44627,
        "elementCount": 6,
        "displayName": 64,
        "hasImage": 0
      }
    },
    {
      "kind": 0,
      "wordVisualType": 0,
      "category": {
        "id": 44618,
        "elementCount": 8,
        "displayName": 96,
        "hasImage": 0
      },
      "wordText": "17+79"
    },
    {
      "kind": 0,
      "wordVisualType": 0,
      "category": {
        "id": 44600,
        "elementCount": 8,
        "displayName": 176,
        "hasImage": 0
      },
      "wordText": "2X88"
    },
    {
      "kind": 0,
      "wordVisualType": 0,
      "category": {
        "id": 44618,
        "elementCount": 8,
        "displayName": 96,
        "hasImage": 0
      },
      "wordText": "101-5"
    },
    {
      "kind": 0,
      "wordVisualType": 0,
      "category": {
        "id": 44618,
        "elementCount": 8,
        "displayName": 96,
        "hasImage": 0
      },
      "wordText": "672/7"
    },
    {
      "kind": 0,
      "wordVisualType": 0,
      "category": {
        "id": 44634,
        "elementCount": 6,
        "displayName": 32,
        "hasImage": 0
      },
      "wordText": "64/2"
    },
    {
      "kind": 0,
      "wordVisualType": 0,
      "category": {
        "id": 44600,
        "elementCount": 8,
        "displayName": 176,
        "hasImage": 0
      },
      "wordText": "167+9"
    },
    {
      "kind": 0,
      "wordVisualType": 0,
      "category": {
        "id": 44600,
        "elementCount": 8,
        "displayName": 176,
        "hasImage": 0
      },
      "wordText": "8X22"
    },
    {
      "kind": 0,
      "wordVisualType": 0,
      "category": {
        "id": 44618,
        "elementCount": 8,
        "displayName": 96,
        "hasImage": 0
      },
      "wordText": "4X24"
    },
    {
      "kind": 0,
      "wordVisualType": 0,
      "category": {
        "id": 44634,
        "elementCount": 6,
        "displayName": 32,
        "hasImage": 0
      },
      "wordText": "14+18"
    },
    {
      "kind": 0,
      "wordVisualType": 0,
      "category": {
        "id": 44618,
        "elementCount": 8,
        "displayName": 96,
        "hasImage": 0
      },
      "wordText": "102-6"
    },
    {
      "kind": 0,
      "wordVisualType": 0,
      "category": {
        "id": 44634,
        "elementCount": 6,
        "displayName": 32,
        "hasImage": 0
      },
      "wordText": "224/7"
    },
    {
      "kind": 0,
      "wordVisualType": 0,
      "category": {
        "id": 44600,
        "elementCount": 8,
        "displayName": 176,
        "hasImage": 0
      },
      "wordText": "184-8"
    },
    {
      "kind": 0,
      "wordVisualType": 0,
      "category": {
        "id": 44634,
        "elementCount": 6,
        "displayName": 32,
        "hasImage": 0
      },
      "wordText": "4X8"
    },
    {
      "kind": 0,
      "wordVisualType": 0,
      "category": {
        "id": 44600,
        "elementCount": 8,
        "displayName": 176,
        "hasImage": 0
      },
      "wordText": "180-4"
    },
    {
      "kind": 0,
      "wordVisualType": 0,
      "category": {
        "id": 44618,
        "elementCount": 8,
        "displayName": 96,
        "hasImage": 0
      },
      "wordText": "11+85"
    },
    {
      "kind": 0,
      "wordVisualType": 0,
      "category": {
        "id": 44600,
        "elementCount": 8,
        "displayName": 176,
        "hasImage": 0
      },
      "wordText": "528/3"
    },
    {
      "kind": 0,
      "wordVisualType": 0,
      "category": {
        "id": 44634,
        "elementCount": 6,
        "displayName": 32,
        "hasImage": 0
      },
      "wordText": "48-16"
    },
    {
      "kind": 0,
      "wordVisualType": 0,
      "category": {
        "id": 44618,
        "elementCount": 8,
        "displayName": 96,
        "hasImage": 0
      },
      "wordText": "768/8"
    },
    {
      "kind": 0,
      "wordVisualType": 0,
      "category": {
        "id": 44634,
        "elementCount": 6,
        "displayName": 32,
        "hasImage": 0
      },
      "wordText": "15+17"
    },
    {
      "kind": 0,
      "wordVisualType": 0,
      "category": {
        "id": 44618,
        "elementCount": 8,
        "displayName": 96,
        "hasImage": 0
      },
      "wordText": "3X32"
    },
    {
      "kind": 0,
      "wordVisualType": 0,
      "category": {
        "id": 44600,
        "elementCount": 8,
        "displayName": 176,
        "hasImage": 0
      },
      "wordText": "79+97"
    },
    {
      "kind": 0,
      "wordVisualType": 0,
      "category": {
        "id": 44609,
        "elementCount": 8,
        "displayName": 132,
        "hasImage": 0
      },
      "wordText": "6X22"
    }
  ]
}